tabular_trees/__init__.py
tabular_trees/checks.py
tabular_trees/explain/__init__.py
tabular_trees/explain/prediction_decomposition.py
tabular_trees/explain/shapley_values.py
tabular_trees/lightgbm/__init__.py
tabular_trees/lightgbm/booster_string.py
tabular_trees/lightgbm/editable_booster.py
tabular_trees/lightgbm/helpers.py
tabular_trees/lightgbm/lightgbm_tabular_trees.py
tabular_trees/sklearn/__init__.py
tabular_trees/sklearn/sklearn_hist_tabular_trees.py
tabular_trees/sklearn/sklearn_tabular_trees.py
tabular_trees/trees.py
tabular_trees/validate.py
tabular_trees/xgboost/__init__.py
tabular_trees/xgboost/dump_parser.py
tabular_trees/xgboost/dump_reader.py
tabular_trees/xgboost/xgboost_tabular_trees.py
tabular_trees-0.3.0.dist-info/LICENSE
tabular_trees-0.3.0.dist-info/METADATA
tabular_trees-0.3.0.dist-info/WHEEL
tabular_trees-0.3.0.dist-info/RECORD
