Metadata-Version: 2.1
Name: tabular-trees
Version: 0.3.0
Summary: Package to assist with analysis of tree-based models.
Home-page: https://github.com/richardangell/tabular-trees
License: BSD-3-Clause
Author: Richard Angell
Author-email: richardangell37@gmail.com
Requires-Python: >=3.9,<4.0
Classifier: License :: OSI Approved :: BSD License
Classifier: Programming Language :: Python :: 3
Classifier: Programming Language :: Python :: 3.9
Classifier: Programming Language :: Python :: 3.10
Classifier: Programming Language :: Python :: 3.11
Classifier: Programming Language :: Python :: 3.12
Provides-Extra: lightgbm
Provides-Extra: sklearn
Provides-Extra: xgboost
Requires-Dist: lightgbm (>=4.5.0,<5.0.0) ; extra == "lightgbm"
Requires-Dist: pandas (>=2.2.0,<3.0.0)
Requires-Dist: scikit-learn (>=1.5.0,<2.0.0) ; extra == "sklearn"
Requires-Dist: tqdm (==4.66.3)
Requires-Dist: typing-extensions (>=4.12.2,<5.0.0)
Requires-Dist: xgboost (>=2.1.0,<3.0.0) ; extra == "xgboost"
Project-URL: Documentation, https://tabular-trees.readthedocs.io/en/latest/
Project-URL: Repository, https://github.com/richardangell/tabular-trees
